dagruff/__init__.py
dagruff/autofix.py
dagruff/cache.py
dagruff/config.py
dagruff/constants.py
dagruff/linter.py
dagruff/logger.py
dagruff/models.py
dagruff/plugins.py
dagruff/validation.py
dagruff/cli/__init__.py
dagruff/cli/linter.py
dagruff/cli/runner.py
dagruff/cli/commands/__init__.py
dagruff/cli/commands/base.py
dagruff/cli/commands/check.py
dagruff/cli/commands/fix.py
dagruff/cli/formatters/__init__.py
dagruff/cli/formatters/human.py
dagruff/cli/formatters/json.py
dagruff/cli/utils/__init__.py
dagruff/cli/utils/args.py
dagruff/cli/utils/autofix_handler.py
dagruff/cli/utils/config_handler.py
dagruff/cli/utils/files.py
dagruff/rules/__init__.py
dagruff/rules/airflint_rules.py
dagruff/rules/ast_collector.py
dagruff/rules/base.py
dagruff/rules/best_practices_rules.py
dagruff/rules/dag_rules.py
dagruff/rules/dagbag.py
dagruff/rules/ruff_air_rules.py
dagruff/rules/utils.py
dagruff-1.0.0.dist-info/METADATA
dagruff-1.0.0.dist-info/WHEEL
dagruff-1.0.0.dist-info/entry_points.txt
dagruff-1.0.0.dist-info/licenses/LICENSE
dagruff-1.0.0.dist-info/RECORD
