Metadata-Version: 2.4
Name: dagruff
Version: 1.0.0
Summary: An extremely fast Python linter for Apache Airflow DAG files
Project-URL: Homepage, https://github.com/dkfancska/dagruff
Project-URL: Documentation, https://github.com/dkfancska/dagruff#readme
Project-URL: Repository, https://github.com/dkfancska/dagruff
Project-URL: Issues, https://github.com/dkfancska/dagruff/issues
Author: DagRuff Contributors
License: MIT
License-File: LICENSE
Keywords: airflow,code-quality,dag,linter,static-analysis
Classifier: Development Status :: 5 - Production/Stable
Classifier: Intended Audience :: Developers
Classifier: License :: OSI Approved :: MIT License
Classifier: Programming Language :: Python
Classifier: Programming Language :: Python :: 3
Classifier: Programming Language :: Python :: 3.9
Classifier: Programming Language :: Python :: 3.10
Classifier: Programming Language :: Python :: 3.11
Classifier: Programming Language :: Python :: 3.12
Classifier: Topic :: Software Development :: Libraries :: Python Modules
Classifier: Topic :: Software Development :: Quality Assurance
Requires-Python: >=3.9
Requires-Dist: tomli>=2.0.0; python_version < '3.11'
Provides-Extra: airflow
Requires-Dist: apache-airflow>=2.5.0; extra == 'airflow'
Provides-Extra: dev
Requires-Dist: pytest-cov>=4.0.0; extra == 'dev'
Requires-Dist: pytest>=7.0.0; extra == 'dev'
Requires-Dist: ruff>=0.1.0; extra == 'dev'
